vinews/__init__.py
vinews/core/__init__.py
vinews/core/constants.py
vinews/core/exceptions.py
vinews/core/models.py
vinews/core/utils.py
vinews/core/interfaces/__init__.py
vinews/core/interfaces/ivinewsparser.py
vinews/core/interfaces/ivinewsscraper.py
vinews/core/interfaces/ivinewssearch.py
vinews/modules/__init__.py
vinews/modules/dantri/__init__.py
vinews/modules/vnexpress/__init__.py
vinews/modules/vnexpress/enums.py
vinews/modules/vnexpress/parsers.py
vinews/modules/vnexpress/scrapers.py
vinews/modules/vnexpress/search.py
vinews-0.1.0.dist-info/METADATA
vinews-0.1.0.dist-info/WHEEL
vinews-0.1.0.dist-info/top_level.txt
vinews-0.1.0.dist-info/RECORD
