Metadata-Version: 2.4
Name: vinews
Version: 0.1.0
Summary: Vinews is an open-source library which provides modules for searching and scraping news data from Vietnamese news websites.
Home-page: https://github.com/JustKiet/vinews
Author: Kiet Do
Author-email: kietdohuu@gmail.com
License: MIT
Project-URL: Bug Reports, https://github.com/JustKiet/vinews/issues
Project-URL: Source, https://github.com/JustKiet/vinews
Project-URL: Documentation, https://github.com/JustKiet/vinews#readme
Keywords: news,scraping,vietnamese,vietnam,web scraping,news scraping
Classifier: Development Status :: 3 - Alpha
Classifier: Intended Audience :: Developers
Classifier: License :: OSI Approved :: MIT License
Classifier: Programming Language :: Python :: 3.12
Classifier: Programming Language :: Python :: 3.13
Classifier: Programming Language :: Python :: 3.14
Classifier: Programming Language :: Python :: 3.15
Classifier: Topic :: Software Development :: Libraries
Requires-Python: >=3.12
Requires-Dist: annotated-types==0.7.0
Requires-Dist: anyio==4.9.0
Requires-Dist: beautifulsoup4==4.13.4
Requires-Dist: certifi==2025.4.26
Requires-Dist: h11==0.16.0
Requires-Dist: httpcore==1.0.9
Requires-Dist: httpx==0.28.1
Requires-Dist: idna==3.10
Requires-Dist: markdownify==1.1.0
Requires-Dist: pydantic==2.11.5
Requires-Dist: pydantic-core==2.33.2
Requires-Dist: six==1.17.0
Requires-Dist: sniffio==1.3.1
Requires-Dist: soupsieve==2.7
Requires-Dist: tenacity==9.1.2
Requires-Dist: typing-extensions==4.14.0
Requires-Dist: typing-inspection==0.4.1
Dynamic: author
Dynamic: author-email
Dynamic: classifier
Dynamic: description
Dynamic: description-content-type
Dynamic: home-page
Dynamic: keywords
Dynamic: license
Dynamic: project-url
Dynamic: requires-dist
Dynamic: requires-python
Dynamic: summary
